Metadata-Version: 2.1
Name: benten-meta
Version: 0.0.1.post4
Summary: benten metadata tool
Home-page: https://github.com/benten-tools/benten-meta
Author: Takahiro Matsumoto
Author-email: matumot@spring8.or.jp
License: Apache License 2.0
Keywords: benten metadata tool
Platform: UNKNOWN
Classifier: Development Status :: 4 - Beta
Classifier: License :: OSI Approved :: Apache Software License
Classifier: Intended Audience :: Developers
Classifier: Programming Language :: Python :: 3
Classifier: Topic :: Database
Classifier: Topic :: Utilities
Classifier: Topic :: Scientific/Engineering :: Physics
